ngocuyenobfx/__init__.py
ngocuyenobfx/__main__.py
ngocuyenobfx/logger.py
ngocuyenobfx/transformers/ControlFlowTransformer.py
ngocuyenobfx/transformers/IfStatementTransformer.py
ngocuyenobfx/transformers/InOutlineTransformer.py
ngocuyenobfx/transformers/MBAExprTransformer.py
ngocuyenobfx/transformers/MemoryTransformer.py
ngocuyenobfx/transformers/OpaqueTransformer.py
ngocuyenobfx/transformers/RenamerTransformer.py
ngocuyenobfx/transformers/StringTransformer.py
ngocuyenobfx/transformers/TryCatchTransformer.py
ngocuyenobfx/transformers/TryNormalizerTransformer.py
ngocuyenobfx/transformers/__init__.py
ngocuyenobfx-0.1.0.dist-info/METADATA
ngocuyenobfx-0.1.0.dist-info/WHEEL
ngocuyenobfx-0.1.0.dist-info/RECORD
