Metadata-Version: 2.1
Name: ngocuyenobfx
Version: 0.1.0
Summary: Mo ta cua package
Author: Ten Tac Gia
Author-email: email@example.com
Requires-Python: >=3.8,<4.0
Classifier: Programming Language :: Python :: 3
Classifier: Programming Language :: Python :: 3.8
Classifier: Programming Language :: Python :: 3.9
Classifier: Programming Language :: Python :: 3.10
Classifier: Programming Language :: Python :: 3.11
Requires-Dist: requests (>=2.31.0,<3.0.0)
